ml_to_en/__init__.py
ml_to_en/ml_to_en.py
ml_to_en-0.0.2.dist-info/METADATA
ml_to_en-0.0.2.dist-info/WHEEL
ml_to_en-0.0.2.dist-info/top_level.txt
ml_to_en-0.0.2.dist-info/RECORD
